[
  {
    "id": "wuxing-intro",
    "title": "五行学说——宇宙的五大基本元素",
    "summary": "五行学说认为宇宙万物由金、木、水、火、土五种基本元素构成，它们之间存在着相生相克的动态关系。",
    "content": "五行学说是中国古代哲学最重要的理论之一，它认为宇宙万物由金、木、水、火、土五种基本元素构成。\n\n【五行的基本属性】\n- 木：具有生长、升发、条达的特性。对应春天、东方，在人体对应肝脏。\n- 火：具有温热、上升、光明的特性。对应夏天、南方，在人体对应心脏。\n- 土：具有生化、承载、受纳的特性。对应长夏、中央，在人体对应脾脏。\n- 金：具有清洁、收敛、肃杀的特性。对应秋天、西方，在人体对应肺脏。\n- 水：具有寒冷、滋润、向下的特性。对应冬天、北方，在人体对应肾脏。\n\n【相生关系——滋养与促进】\n木生火——木材燃烧产生火焰\n火生土——火焰燃烧后化为灰烬\n土生金——金属从矿石中提炼\n金生水——金属表面凝结水珠\n水生木——水滋养树木生长\n这样就构成了一个循环促进的链条：木→火→土→金→水→木。\n\n【相克关系——制约与平衡】\n木克土——树木的根可以固定土壤\n火克金——烈火可以熔化金属\n土克水——堤坝可以阻挡水流\n金克木——金属刀具可以砍伐树木\n水克火——水可以扑灭火焰\n这样就构成了一个循环制约的链条：木→土→水→火→金→木。\n\n【乘侮关系——异常的克制】\n在五行系统中，如果某一行过强或过弱，就会打破正常的生克平衡，出现「相乘」（过度克制）或「相侮」（反向克制）的异常关系。\n\n【应用领域】\n五行学说在中医、命理、风水、音乐、兵法等诸多领域都有广泛应用。\n五行的核心思想是「平衡」——五行平衡则万物和谐，五行失衡则灾祸生。",
    "tags": [
      "五行",
      "相生相克",
      "金木水火土",
      "基础"
    ]
  },
  {
    "id": "wuxing-application",
    "title": "五行的对应关系表",
    "summary": "五行学说建立了一套精密的对应系统，将自然现象、人体器官、颜色、味道等纳入其中。",
    "content": "五行学说最迷人的地方之一是它建立了一套精密的对应系统，将万事万物归类到五行之中。\n\n【五行对照总表】\n\n五方：木(东)  火(南)  土(中)  金(西)  水(北)\n五季：木(春)  火(夏)  土(长夏) 金(秋)  水(冬)\n五色：木(青)  火(赤)  土(黄)  金(白)  水(黑)\n五味：木(酸)  火(苦)  土(甘)  金(辛)  水(咸)\n五脏：木(肝)  火(心)  土(脾)  金(肺)  水(肾)\n五窍：木(目)  火(舌)  土(口)  金(鼻)  水(耳)\n五体：木(筋)  火(脉)  土(肉)  金(皮)  水(骨)\n五志：木(怒)  火(喜)  土(思)  金(悲)  水(恐)\n五德：木(仁)  火(礼)  土(信)  金(义)  水(智)\n\n【五行与天干地支】\n天干：甲乙属木、丙丁属火、戊己属土、庚辛属金、壬癸属水\n地支：寅卯属木、巳午属火、辰戌丑未属土、申酉属金、亥子属水\n\n【五行与八卦】\n震巽属木、离属火、坤艮属土、乾兑属金、坎属水。\n\n这套对应系统体现了古人的「天人合一」思想——人体小宇宙与自然大宇宙之间存在全息对应关系。",
    "tags": [
      "五行",
      "对应表",
      "五脏",
      "颜色",
      "方位"
    ]
  }
]
